{
    "server_host": "127.0.0.1",
    "server_port": 5017,
    "resource_path": [
        "device",
        "data"
    ],
    "coordinate": {
        "latitude": -18.8923,
        "longitude": -48.3837
    },
    "temperature_range": [
        18.0,
        32.0
    ],
    "drop_percentage": 13,
    "delay_profiles": [
        {
            "probability": 70,
            "min": 0.119,
            "max": 0.249
        },
        {
            "probability": 30,
            "min": 0.399,
            "max": 1.321
        }
    ],
    "uuid": "c1b79a45-03d0-4b46-b9a7-1166f8f6d364",
    "battery_idle_discharge": 0.0788279799754293,
    "battery_transmit_discharge": 0.3504105596196403,
    "battery_charge": 56
}